{
  "items": [
    {
      "buttonText": "hold your breath.",
      "description": "Poetry penned and collected over time and transitions. Caveat emptor: not a lot of sunshine and rainbows within.",
      "destination": "/studio/hfc",
      "image": "https://ik.imagekit.io/tempoimmaterial/studio/piano-hfc.jpg?tr=w-316,h-476,fo-right",
      "imageAlt": "A crumbled grand piano in front of a ruined building.",
      "order": 1,
      "published": true,
      "shortenedLogoText": "hfc",
      "subtitle": "poems",
      "title": "hymns for calliope"
    },
    {
      "buttonText": "grab some popcorn.",
      "description": "A recently-designed website for the cinematography of Shorouk Elkobrsi.",
      "destination": "https://shoroukelkobrsi.com",
      "image": "https://ik.imagekit.io/tempoimmaterial/studio/Cinematographer_s%20room.jpg?tr=w-316,h-476",
      "imageAlt": "Reels of film spooled over each other.",
      "order": 2,
      "published": true,
      "shortenedLogoText": "s/a",
      "subtitle": "cinema",
      "title": "anthro-potpourri"
    },
    {
      "buttonText": "this house used to be so much bigger.",
      "description": "Retellings of my own fractured existence. Always true even if the facts are bullshit.",
      "destination": "/blog/two-truths-and-a-lie",
      "image": "https://ik.imagekit.io/tempoimmaterial/studio/look.jpg?tr=w-316,h-476",
      "imageAlt": "Hair on backwards, completely covering the gaze.",
      "order": 3,
      "published": true,
      "shortenedLogoText": "tt",
      "subtitle": "essays",
      "title": "tall tales"
    },
    {
      "buttonText": "turn it up.",
      "description": "Musical musings and improvs, collected here for you to listen and relax.",
      "destination": "https://soundcloud.com/tempoimmaterial",
      "image": "https://ik.imagekit.io/tempoimmaterial/studio/city-j.jpg?tr=w-316,h-476,fo-bottom_right",
      "imageAlt": "A light-stained highway and city at night.",
      "order": 4,
      "published": true,
      "shortenedLogoText": "j",
      "subtitle": "compositions",
      "title": "jukebox"
    },
    {
      "buttonText": "to the museum.",
      "description": "A small collection of digital paintings, rendered out brushstroke by brushstroke.",
      "destination": "/studio/illustrations",
      "image": "https://ik.imagekit.io/tempoimmaterial/studio/flower-p.jpg?tr=w-316,h-476",
      "imageAlt": "A single flower open against the dark.",
      "order": 5,
      "published": true,
      "shortenedLogoText": "art",
      "subtitle": "visual art",
      "title": "illustrations"
    },
    {
      "buttonText": "get lost, loser.",
      "description": "A tall tale firmly rooted in the Midwest gothic, full of ghosts and kids just trying to make it through.",
      "destination": "/studio/betson",
      "image": "https://ik.imagekit.io/tempoimmaterial/studio/water%20sloshing?tr=w-316,h-476",
      "imageAlt": "Fresh crick water sloshing against the frame.",
      "order": 6,
      "published": true,
      "shortenedLogoText": "bet",
      "subtitle": "novel in calendar",
      "title": "betson"
    },
    {
      "buttonText": "lick the envelope.",
      "description": "Flash and other fiction that just keep happening (and are impossible to collect elsewhere).",
      "destination": "/studio/postcards",
      "image": "https://ik.imagekit.io/tempoimmaterial/studio/Nebula.jpg?tr=316,h-476",
      "imageAlt": "A nebula bursting against the yawning maw of space.",
      "order": 7,
      "published": true,
      "shortenedLogoText": "pc",
      "subtitle": "sudden stories",
      "title": "postcards"
    },
    {
      "buttonText": "dive in.",
      "description": "A sprawl filled with lovers and fiends, all striving to remember an ever-erasing past.",
      "destination": "/studio/tmi",
      "image": "https://ik.imagekit.io/tempoimmaterial/studio/Magic%20forest%20of%20mushrooms..jpg?tr=w-316,h-476",
      "imageAlt": "A forest of mushrooms.",
      "order": 8,
      "published": true,
      "shortenedLogoText": "tmi",
      "subtitle": "a shifting, tilting world",
      "title": "these makeshift idiotika"
    },
    {
      "buttonText": "play the highlight reel.",
      "description": "A growing list of achievements and milestones as I work with Vercel on telling the story of the Frontend Cloud.",
      "destination": "/vercel",
      "image": "https://ik.imagekit.io/tempoimmaterial/studio/triangle?tr=w-316,h-476",
      "imageAlt": "Flowers in front of a triangular window.",
      "order": 9,
      "published": false,
      "shortenedLogoText": "v",
      "subtitle": "technical marketing",
      "title": "vercel"
    },
    {
      "buttonText": "see the source, Neo.",
      "description": "A detailed account of coding this website by hand.",
      "destination": "https://github.com/3mdistal/portfolio",
      "image": "https://ik.imagekit.io/tempoimmaterial/studio/Pool%20Life.jpg?tr=w-316,h-476",
      "imageAlt": "A grid of blue squares.",
      "order": 10,
      "published": true,
      "shortenedLogoText": "010",
      "subtitle": "creative web development",
      "title": "blueprints"
    },
    {
      "buttonText": "don't startle the birds.",
      "description": "A series of evocative essays by the lovely Vic Ardelle. Website, illustrations, and Vic's pen name by yours truly.",
      "destination": "https://www.birdsofmalaiseville.com/",
      "image": "https://ik.imagekit.io/tempoimmaterial/studio/Nest..jpg?tr=w-316,h-476",
      "imageAlt": "A bird's nest with two pale eggs.",
      "order": 11,
      "published": true,
      "shortenedLogoText": "bom",
      "subtitle": "spiritual discontentment enters late middle age",
      "title": "birds of malaiseville"
    },
    {
      "buttonText": "grab your controller.",
      "description": "An ever-growing collection of HTML canvas experiments, eventually evolving into full games written in JavaScript.",
      "destination": "/studio/arcade",
      "image": "https://ik.imagekit.io/tempoimmaterial/studio/oldgames?tr=w-316,h-476",
      "imageAlt": "Old consoles stacked on a table.",
      "order": 12,
      "published": true,
      "shortenedLogoText": "arc",
      "subtitle": "interactive experimentation",
      "title": "arcade"
    },
    {
      "buttonText": "learn about it all.",
      "description": "Stay tuned for a whole lot of projects I have in the works.",
      "destination": "/blog/on-continuous-resurrection",
      "image": "https://ik.imagekit.io/tempoimmaterial/studio/ink.png?tr=w-316,h-476",
      "imageAlt": "All blue.",
      "order": 13,
      "published": true,
      "shortenedLogoText": "&",
      "subtitle": "",
      "title": "and more to come…"
    }
  ]
}
